cldz_cli/__init__.py
cldz_cli/cldz_cli.py
cldz_cli-0.1.1.dist-info/entry_points.txt
cldz_cli-0.1.1.dist-info/WHEEL
cldz_cli-0.1.1.dist-info/METADATA
cldz_cli-0.1.1.dist-info/RECORD
