Metadata-Version: 2.1
Name: cldz-cli
Version: 0.1.1
Summary: 
Author: Rohan Kothapalli
Author-email: rohan.kothapalli@clouderizer.com
Requires-Python: >=3.5,<4.0
Classifier: Programming Language :: Python :: 3
Classifier: Programming Language :: Python :: 3.5
Classifier: Programming Language :: Python :: 3.6
Classifier: Programming Language :: Python :: 3.7
Classifier: Programming Language :: Python :: 3.8
Classifier: Programming Language :: Python :: 3.9
Requires-Dist: PyJWT (>=1.7.0,<2.0.0)
Requires-Dist: coolname (>=1.1.0,<2.0.0)
Requires-Dist: fire (>=0.3.1,<0.4.0)
Requires-Dist: pipreqs (>=0.4.0,<0.5.0)
Requires-Dist: prettytable (>=0.7.2,<0.8.0)
Requires-Dist: requests (>=2.7.0,<3.0.0)
Requires-Dist: requirements-parser (>=0.2.0,<0.3.0)
